moop/__init__.py
moop/__main__.py
moop/compat.py
moop/config.py
moop/exceptions.py
moop/logger.py
moop/moop.py
moop/version.py
moop-0.1.0.dist-info/LICENSE
moop-0.1.0.dist-info/METADATA
moop-0.1.0.dist-info/WHEEL
moop-0.1.0.dist-info/entry_points.txt
moop-0.1.0.dist-info/RECORD
